bpd/__init__.py
bpd/config.yml
bpd/dataframe.py
bpd/dask/__init__.py
bpd/dask/backend.py
bpd/dask/daskframe.py
bpd/dask/dataframe.py
bpd/dask/functions.py
bpd/dask/pipelines.py
bpd/dask/types/__init__.py
bpd/pandas/__init__.py
bpd/pandas/dataframe.py
bpd/pyspark/__init__.py
bpd/pyspark/backend.py
bpd/pyspark/dataframe.py
bpd/pyspark/functional.py
bpd/pyspark/udf/__init__.py
bpd/tests/__init__.py
bpd/tests/__main__.py
bpd/tests/test_bpd.py
bpd-0.1.0.dist-info/METADATA
bpd-0.1.0.dist-info/WHEEL
bpd-0.1.0.dist-info/top_level.txt
bpd-0.1.0.dist-info/RECORD
