Metadata-Version: 2.1
Name: bpd
Version: 0.1.0
Summary: bpd
Home-page: https://github.com/zakuro-ai/bpd
Author: CADIC Jean-Maximilien
Author-email: git@zakuro.ai
License: MIT
Platform: linux_debian_10_x86_64
Classifier: Programming Language :: Python :: 3
Classifier: License :: OSI Approved :: MIT License
Requires-Python: >=3.6
Requires-Dist: numpy
Requires-Dist: pandas
Requires-Dist: gnutools-python
Requires-Dist: tqdm
Requires-Dist: pyspark
Requires-Dist: distributed
Requires-Dist: jupyter
Requires-Dist: jupyterlab
